<?xml version="1.0" encoding="UTF-8"?>
<CompileSettings>
    <ProjectSettings>
        <Content Scope="Included">
            <Filter State="Off" Exclude="No" Type="Label">
                <CollectionID>F1733FDE-DF32-477E-AB8E-0D8016E67AD5</CollectionID>
                <Label>-1</Label>
                <Status>-1</Status>
            </Filter>
        </Content>
        <Options>
            <RemoveComments>Yes</RemoveComments>
            <RemoveAnnotations>Yes</RemoveAnnotations>
            <ResampleImages DPI="72">No</ResampleImages>
            <ConvertTablesAndListToMMD>Yes</ConvertTablesAndListToMMD>
            <PDF>
                <Cover Source="FrontMatter" Bleed="9.0" BleedUnits="pt"/>
                <Compression Enabled="No">
                    <ImageResolutionCompressionType>Set</ImageResolutionCompressionType>
                    <ImageResolution>150</ImageResolution>
                    <CompressionQuality>0.5</CompressionQuality>
                </Compression>
            </PDF>
            <Scriptwriting>
                <IncludeTitles>Yes</IncludeTitles>
                <IncludeSynopses>Yes</IncludeSynopses>
                <CommentsAsScriptNotes>Yes</CommentsAsScriptNotes>
            </Scriptwriting>
            <Ebook>
                <StartAfterFrontMatter>Yes</StartAfterFrontMatter>
                <Cover>
                    <ImageDocument Source="FrontMatter"/>
                    <Title>Cover</Title>
                    <SVG Width="600" Height="800"><![CDATA[]]></SVG>
                </Cover>
                <TOC PandocDepth="3">
                    <HTML Generate="Yes">
                        <Title>Contents</Title>
                    </HTML>
                </TOC>
            </Ebook>
        </Options>
        <MetaData>
            <ProjectTitle>Javascript Concurrency</ProjectTitle>
            <ProjectAbbreviatedTitle>Javascript Concurrency</ProjectAbbreviatedTitle>
            <EbookLanguage>en</EbookLanguage>
            <FountainTitlePageMetaData>
                <Value Key="Title"><![CDATA[<$projecttitle>]]></Value>
                <Value Key="Author"><![CDATA[<$author>]]></Value>
            </FountainTitlePageMetaData>
            <MMDMetaData>
                <Value Key="Title"><![CDATA[<$projecttitle>]]></Value>
                <Value Key="Author"><![CDATA[<$author>]]></Value>
            </MMDMetaData>
        </MetaData>
    </ProjectSettings>
    <CurrentFileType>html</CurrentFileType>
    <FormatSettings>
        <Format ID="DEFAULT">
            <SectionLayouts>
                <Type ID="761151E1-5036-4FE6-8142-38EF3B1ED381">NEW-PAGE-HEADER-WITH-TEXT</Type>
                <Type ID="82F1694C-7A6A-4EAA-94B9-3F0D29AA1638">TEXT-SECTION</Type>
            </SectionLayouts>
        </Format>
    </FormatSettings>
    <LastUsedFormats>
        <Print>DEFAULT</Print>
        <html>DEFAULT</html>
    </LastUsedFormats>
</CompileSettings>