<?xml version="1.0" encoding="UTF-8"?>
<Styles>
    <Style Name="Title" ID="0CB76449-3411-4FCE-A96C-0E1DCD71B67C" Type="Para+Char" FontChange="Size">
        <Format><![CDATA[{\rtf1\ansi\ansicpg1252\cocoartf1561\cocoasubrtf610
{\fonttbl\f0\froman\fcharset0 Palatino-Roman;}
{\colortbl;\red255\green255\blue255;}
{\*\expandedcolortbl;;}
\pard\tx560\tx1120\tx1680\tx2240\tx2800\tx3360\tx3920\tx4480\tx5040\tx5600\tx6160\tx6720\sl264\slmult1\sb260\pardirnatural\partightenfactor0

\f0\fs56 \cf0 <$ScrKeepWithNext>Attributes}]]></Format>
    </Style>
    <Style Name="Heading 1" ID="993EC2A7-8C02-4E0F-A84D-734154688861" Type="Para+Char" FontChange="Size" Shortcut="4">
        <Format><![CDATA[{\rtf1\ansi\ansicpg1252\cocoartf1561\cocoasubrtf610
{\fonttbl\f0\fswiss\fcharset0 Helvetica;\f1\froman\fcharset0 Palatino-Roman;}
{\colortbl;\red255\green255\blue255;}
{\*\expandedcolortbl;;}
\pard\tx560\tx1120\tx1680\tx2240\tx2800\tx3360\tx3920\tx4480\tx5040\tx5600\tx6160\tx6720\sl264\slmult1\sb260\pardirnatural\partightenfactor0

\f0\fs24 \cf0 <$ScrKeepWithNext><$Scr_H::1>
\f1\b\fs36 Attributes
\f0\b0\fs24 <!$Scr_H::1>}]]></Format>
    </Style>
    <Style Name="Heading 2" ID="D91E004F-A028-48F7-8C6F-81132F9CE5F3" Type="Para+Char" FontChange="Size" Shortcut="5">
        <Format><![CDATA[{\rtf1\ansi\ansicpg1252\cocoartf1561\cocoasubrtf610
{\fonttbl\f0\fswiss\fcharset0 Helvetica;\f1\froman\fcharset0 Palatino-Roman;}
{\colortbl;\red255\green255\blue255;}
{\*\expandedcolortbl;;}
\pard\tx560\tx1120\tx1680\tx2240\tx2800\tx3360\tx3920\tx4480\tx5040\tx5600\tx6160\tx6720\sl264\slmult1\sb260\pardirnatural\partightenfactor0

\f0\fs24 \cf0 <$ScrKeepWithNext><$Scr_H::2>
\f1\b\fs26 Attributes
\f0\b0\fs24 <!$Scr_H::2>}]]></Format>
    </Style>
    <Style Name="Centered Text" ID="4178773C-3CF1-49E2-949B-842C704EF779" Type="Para" Shortcut="1">
        <Format><![CDATA[{\rtf1\ansi\ansicpg1252\cocoartf1561\cocoasubrtf610
{\fonttbl\f0\froman\fcharset0 Palatino-Roman;}
{\colortbl;\red255\green255\blue255;}
{\*\expandedcolortbl;;}
\pard\tx360\tx720\tx1080\tx1440\tx1800\tx2160\tx2880\tx3600\tx4320\sl264\slmult1\pardirnatural\qc\partightenfactor0

\f0\fs26 \cf0 Attributes}]]></Format>
    </Style>
    <Style Name="Block Quote" ID="B99D71A6-F580-437C-A8E0-C0D2122A4D74" Type="Para" FontChange="Size" Shortcut="2">
        <Format><![CDATA[{\rtf1\ansi\ansicpg1252\cocoartf1561\cocoasubrtf610
{\fonttbl\f0\froman\fcharset0 Palatino-Roman;}
{\colortbl;\red255\green255\blue255;}
{\*\expandedcolortbl;;}
\pard\tx720\tx1080\tx1440\li720\sl264\slmult1\sb240\sa240\pardirnatural\partightenfactor0

\f0\fs24 \cf0 Attributes}]]></Format>
    </Style>
    <Style Name="Attribution" ID="FB232C78-C014-47DA-A022-15AF018B0D9F" Type="Para" FontChange="Size" Shortcut="">
        <Format><![CDATA[{\rtf1\ansi\ansicpg1252\cocoartf1561\cocoasubrtf610
{\fonttbl\f0\froman\fcharset0 Palatino-Roman;}
{\colortbl;\red255\green255\blue255;}
{\*\expandedcolortbl;;}
\pard\tx720\tx1080\tx1440\li720\sl264\slmult1\sa240\pardirnatural\qr\partightenfactor0

\f0\fs24 \cf0 Attributes}]]></Format>
    </Style>
    <Style Name="Code Block" ID="FE25E53F-DF36-439B-BABE-F475DD0C8B9B" Type="Para+Char" FontChange="Face+Size" Next="FE25E53F-DF36-439B-BABE-F475DD0C8B9B">
        <Format><![CDATA[{\rtf1\ansi\ansicpg1252\cocoartf1561\cocoasubrtf610
{\fonttbl\f0\fnil\fcharset0 Menlo-Regular;}
{\colortbl;\red255\green255\blue255;}
{\*\expandedcolortbl;;}
\pard\tx720\tx1080\tx1440\tx1800\tx2160\li720\pardirnatural\partightenfactor0

\f0\fs22 \cf0 Attributes}]]></Format>
    </Style>
    <Style Name="Verse" ID="FD848038-E1EE-470E-858D-8FDDAAC5681C" Type="Para" FontChange="Size" Next="FD848038-E1EE-470E-858D-8FDDAAC5681C">
        <Format><![CDATA[{\rtf1\ansi\ansicpg1252\cocoartf1561\cocoasubrtf610
{\fonttbl\f0\froman\fcharset0 Palatino-Roman;}
{\colortbl;\red255\green255\blue255;}
{\*\expandedcolortbl;;}
\pard\sl264\slmult1\pardirnatural\qc\partightenfactor0

\f0\fs24 \cf0 Attributes}]]></Format>
    </Style>
    <Style Name="Code Span" ID="7306F067-4ADC-420F-B526-64705398062C" Type="Char" FontChange="Face+Size">
        <Format><![CDATA[{\rtf1\ansi\ansicpg1252\cocoartf1561\cocoasubrtf610
{\fonttbl\f0\fnil\fcharset0 Menlo-Regular;}
{\colortbl;\red255\green255\blue255;}
{\*\expandedcolortbl;;}
\pard\tx720\tx1080\tx1440\tx1800\tx2160\li720\pardirnatural\partightenfactor0

\f0\fs22 \cf0 Attributes}]]></Format>
    </Style>
    <Style Name="Caption" ID="B75BE972-AD9E-4E3D-B95A-0680D3CC44A1" Type="Para" FontChange="Size" Shortcut="3">
        <Format><![CDATA[{\rtf1\ansi\ansicpg1252\cocoartf1561\cocoasubrtf610
{\fonttbl\f0\froman\fcharset0 Palatino-Roman;}
{\colortbl;\red255\green255\blue255;}
{\*\expandedcolortbl;;}
\pard\tx560\tx1120\tx1680\tx2240\tx2800\tx3360\tx3920\tx4480\tx5040\tx5600\tx6160\tx6720\sl264\slmult1\sa160\pardirnatural\qc\partightenfactor0

\f0\fs26 \cf0 Attributes}]]></Format>
    </Style>
    <Style Name="Emphasis" ID="4FB1247D-DF2A-45C5-8A9F-C29AB3E2BD14" Type="Char">
        <Format><![CDATA[{\rtf1\ansi\ansicpg1252\cocoartf1561\cocoasubrtf610
{\fonttbl\f0\froman\fcharset0 Palatino-Roman;}
{\colortbl;\red255\green255\blue255;}
{\*\expandedcolortbl;;}
\pard\tx360\tx720\tx1080\tx1440\tx1800\tx2160\tx2880\tx3600\tx4320\fi360\sl264\slmult1\pardirnatural\partightenfactor0

\f0\i\fs26 \cf0 Attributes}]]></Format>
    </Style>
</Styles>